{
  "skill_synonyms": {
    "AWS": ["Amazon Web Services", "aws", "amazon web services"],
    "Kubernetes": ["K8s", "k8s", "kubernetes"],
    "Docker": ["docker", "containerization"],
    "Jenkins": ["jenkins"],
    "CI/CD": ["CI CD", "CICD", "Continuous Integration", "Continuous Deployment", "Continuous Delivery"],
    "Git": ["git", "version control"],
    "GitHub": ["github", "Github"],
    "GitLab": ["gitlab", "Gitlab", "GitLab CI", "GitLab CI/CD"],
    "Python": ["python", "python3"],
    "JavaScript": ["javascript", "js", "JS", "ECMAScript"],
    "TypeScript": ["typescript", "ts", "TS"],
    "Node.js": ["nodejs", "node", "NodeJS"],
    "React": ["react", "reactjs", "React.js", "ReactJS"],
    "Angular": ["angular", "angularjs", "Angular.js"],
    "Vue": ["vue", "vuejs", "Vue.js", "VueJS"],
    "PostgreSQL": ["postgres", "postgresql", "PostgresSQL"],
    "MySQL": ["mysql", "My SQL"],
    "MongoDB": ["mongodb", "mongo"],
    "SQL": ["sql", "structured query language"],
    "NoSQL": ["nosql", "no sql"],
    "Machine Learning": ["ML", "ml", "machine learning"],
    "Deep Learning": ["DL", "dl", "deep learning"],
    "Natural Language Processing": ["NLP", "nlp", "natural language processing"],
    "TensorFlow": ["tensorflow", "Tensorflow"],
    "PyTorch": ["pytorch", "Pytorch", "torch"],
    "Scikit-learn": ["sklearn", "scikit-learn", "scikit learn"],
    "Pandas": ["pandas"],
    "NumPy": ["numpy", "Numpy"],
    "REST API": ["REST", "RESTful", "REST API", "RESTful API", "rest api"],
    "GraphQL": ["graphql", "Graph QL"],
    "Terraform": ["terraform"],
    "Ansible": ["ansible"],
    "Grafana": ["grafana"],
    "Prometheus": ["prometheus"],
    "Splunk": ["splunk"],
    "Linux": ["linux", "unix", "Ubuntu", "RHEL", "Red Hat", "CentOS", "Debian"],
    "Bash": ["bash", "shell scripting", "shell script", "bash scripting"],
    "Azure": ["azure", "Microsoft Azure", "ms azure"],
    "GCP": ["GCP", "Google Cloud", "Google Cloud Platform", "gcp"],
    "EC2": ["ec2", "Elastic Compute Cloud"],
    "S3": ["s3", "Simple Storage Service"],
    "Lambda": ["lambda", "AWS Lambda"],
    "ECS": ["ecs", "Elastic Container Service"],
    "EKS": ["eks", "Elastic Kubernetes Service"],
    "CloudWatch": ["cloudwatch", "Cloud Watch"],
    "VPC": ["vpc", "Virtual Private Cloud"],
    "IAM": ["iam", "Identity and Access Management"],
    "RDS": ["rds", "Relational Database Service"],
    "Agile": ["agile", "agile methodology"],
    "Scrum": ["scrum"],
    "DevOps": ["devops", "dev ops"],
    "SRE": ["Site Reliability Engineering", "sre", "site reliability"],
    "Microservices": ["microservices", "micro services", "microservice architecture"],
    "API": ["api", "Application Programming Interface"],
    "HTML": ["html", "html5", "HTML5"],
    "CSS": ["css", "css3", "CSS3"],
    "Django": ["django"],
    "Flask": ["flask"],
    "FastAPI": ["fastapi", "fast api"],
    "Express": ["express", "expressjs", "express.js"],
    "Spring Boot": ["spring boot", "springboot", "spring"],
    "ASP.NET": ["asp.net", "aspnet", "ASP.NET Core", "asp.net core"],
    "Jira": ["jira"],
    "Confluence": ["confluence"],
    "Elasticsearch": ["elasticsearch", "elastic search"],
    "Redis": ["redis"],
    "Cassandra": ["cassandra"],
    "Kafka": ["kafka", "Apache Kafka"],
    "Spark": ["spark", "Apache Spark", "pyspark"],
    "Airflow": ["airflow", "Apache Airflow"],
    "Helm": ["helm"],
    "ArgoCD": ["argocd", "argo cd", "argo"],
    "GitOps": ["gitops", "git ops"],
    "CloudFormation": ["cloudformation", "cloud formation"],
    "ELK Stack": ["ELK", "elk", "Elasticsearch Logstash Kibana"],
    "Logstash": ["logstash"],
    "Kibana": ["kibana"],
    "Datadog": ["datadog", "data dog"],
    "New Relic": ["newrelic", "new relic"],
    "AppDynamics": ["appdynamics", "app dynamics"],
    "Zabbix": ["zabbix"],
    "Nagios": ["nagios"],
    "SLO": ["SLO", "Service Level Objective", "slo"],
    "SLI": ["SLI", "Service Level Indicator", "sli"],
    "SLA": ["SLA", "Service Level Agreement", "sla"],
    "ETL": ["ETL", "Extract Transform Load", "etl"],
    "High Availability": ["HA", "high availability", "ha"],
    "Disaster Recovery": ["DR", "disaster recovery", "dr"],
    "Load Balancer": ["load balancing", "load balancer", "lb"],
    "Nginx": ["nginx", "NGINX"],
    "HAProxy": ["haproxy", "ha proxy"],
    "Container Security": ["container security"],
    "OWASP": ["owasp"],
    "Penetration Testing": ["pentesting", "pen testing", "penetration testing"],
    "Network Security": ["network security"],
    "Cryptography": ["cryptography", "encryption"],
    "OAuth": ["oauth", "OAuth2", "oauth2"],
    "SAML": ["saml"],
    "SSO": ["sso", "Single Sign-On", "single sign on"],
    "RBAC": ["rbac", "Role-Based Access Control"],
    "MFA": ["mfa", "Multi-Factor Authentication", "2FA", "two factor"],
    "TDD": ["TDD", "Test-Driven Development", "test driven development"],
    "BDD": ["BDD", "Behavior-Driven Development", "behavior driven development"],
    "Selenium": ["selenium"],
    "Jest": ["jest"],
    "Pytest": ["pytest", "py.test"],
    "JUnit": ["junit", "j unit"],
    "JMeter": ["jmeter", "j meter"],
    "Postman": ["postman"],
    "Swagger": ["swagger", "OpenAPI", "open api"],
    "Groovy": ["groovy"],
    "PowerShell": ["powershell", "power shell"],
    "Vault": ["vault", "HashiCorp Vault", "hashicorp vault"],
    "Snyk": ["snyk"],
    "SonarQube": ["sonarqube", "sonar qube", "sonar"],
    "Tableau": ["tableau"],
    "Power BI": ["powerbi", "power bi"],
    "Matplotlib": ["matplotlib"],
    "Seaborn": ["seaborn"],
    "Plotly": ["plotly"]
  }
}